ayla_iot_unofficial/__init__.py
ayla_iot_unofficial/ayla_iot_unofficial.py
ayla_iot_unofficial/const.py
ayla_iot_unofficial/device.py
ayla_iot_unofficial/exc.py
ayla_iot_unofficial/fujitsu_consts.py
ayla_iot_unofficial/fujitsu_hvac.py
ayla_iot_unofficial-1.5.0.dist-info/licenses/LICENSE
ayla_iot_unofficial-1.5.0.dist-info/METADATA
ayla_iot_unofficial-1.5.0.dist-info/WHEEL
ayla_iot_unofficial-1.5.0.dist-info/top_level.txt
ayla_iot_unofficial-1.5.0.dist-info/RECORD
