Metadata-Version: 2.4
Name: ayla_iot_unofficial
Version: 1.5.0
Summary: Python API for Ayla IoT products
Home-page: https://github.com/rewardone/ayla-iot-unofficial
Author: Reward One
Author-email: Reward One <rewardone.com@gmail.com>
Project-URL: Homepage, https://github.com/rewardone/ayla-iot-unofficial
Project-URL: Bug Tracker, https://github.com/rewardone/ayla-iot-unofficial/issues
Classifier: Programming Language :: Python :: 3
Classifier: License :: OSI Approved :: MIT License
Classifier: Operating System :: OS Independent
Requires-Python: >=3.7
License-File: LICENSE
Requires-Dist: aiohttp>=3.8.4
Requires-Dist: requests>=2.31.0
Requires-Dist: ujson>=5.8.0
Dynamic: author
Dynamic: home-page
Dynamic: license-file
